lisa/__init__.py
lisa/gateway.py
model/__init__.py
model/gateway.py
gateway_lisa-0.0.2.dist-info/LICENSE
gateway_lisa-0.0.2.dist-info/METADATA
gateway_lisa-0.0.2.dist-info/WHEEL
gateway_lisa-0.0.2.dist-info/top_level.txt
gateway_lisa-0.0.2.dist-info/RECORD
