Metadata-Version: 2.1
Name: gateway-lisa
Version: 0.0.2
Summary: A gateway package
Home-page: https://github.com/matfonseca/gateway-lisa
Author: Matias Fonseca
Author-email: mfonseca@fi.uba.ar
License: UNKNOWN
Platform: UNKNOWN
Classifier: Programming Language :: Python :: 3
Classifier: License :: OSI Approved :: MIT License
Classifier: Operating System :: OS Independent
License-File: LICENSE
